[{"name":"Abercorn"},{"name":"Adderly"},{"name":"Adelaide"},{"name":"Albert Town"},{"name":"Alexander"},{"name":"Allen"},{"name":"Alligator Bay Settlement"},{"name":"Anderson"},{"name":"Andersons"},{"name":"Andros Town"},{"name":"Anne's Tract Settlement"},{"name":"August Town"},{"name":"Bailey Town"},{"name":"Bain Town"},{"name":"Bains"},{"name":"Bannerman Town"},{"name":"Baraterre"},{"name":"Bastian Point"},{"name":"Behring Point"},{"name":"Bennetts Harbor"},{"name":"Berrys"},{"name":"Betsy Bay"},{"name":"Bevans Town"},{"name":"Binnacle Hill"},{"name":"Blackwood Village"},{"name":"Blanket Sound"},{"name":"Bluff Settlement"},{"name":"Bowen Sound"},{"name":"Bowers"},{"name":"Bradford"},{"name":"Brandy Hill"},{"name":"Braudies Point"},{"name":"Browns"},{"name":"Buckleys"},{"name":"Bullocks Harbour"},{"name":"Burnt Ground"},{"name":"Cabbage Hill"},{"name":"Cabbage Point"},{"name":"Cairey's"},{"name":"Calabash Bay"},{"name":"Calvin Hill"},{"name":"Camperdown"},{"name":"Cargill Creek"},{"name":"Carmichael Village"},{"name":"Cartwright"},{"name":"Cedar Harbour"},{"name":"Cherokee Sound"},{"name":"Chesters"},{"name":"Chub Cay"},{"name":"Church Grove"},{"name":"Clifton"},{"name":"Coakley Town"},{"name":"Colebrooke Dale"},{"name":"Conch Sound Settlement"},{"name":"Congo Town"},{"name":"Cooper's Town"},{"name":"Coral Harbour"},{"name":"Coral Heights"},{"name":"Cornishtown"},{"name":"Cove"},{"name":"Creek Village"},{"name":"Cripple Hill"},{"name":"Crossing Rocks"},{"name":"Crown Haven"},{"name":"Cunningham"},{"name":"Current Island Settlement"},{"name":"Current"},{"name":"Curtis"},{"name":"Davis Harbor"},{"name":"Deadman's Cay"},{"name":"Deep Creek"},{"name":"Delancey Town"},{"name":"Delectable Point"},{"name":"Devil's Point"},{"name":"Dixons"},{"name":"Doctor's Creek"},{"name":"Douds"},{"name":"Driggs Hill"},{"name":"Dumfries"},{"name":"Dundas Town"},{"name":"Dunmore Town"},{"name":"Dunmore"},{"name":"Eight Mile Rock"},{"name":"Eleuthera"},{"name":"Fairfield"},{"name":"Farmer's Hill"},{"name":"Farquharson"},{"name":"Fire Road Village"},{"name":"Forbes Hill"},{"name":"Ford"},{"name":"Forest"},{"name":"Fortune Hill"},{"name":"Fox Town"},{"name":"Freetown"},{"name":"French Wells"},{"name":"Gaitor's"},{"name":"Galloway Landing"},{"name":"Gambier Village"},{"name":"Gilbert Grant"},{"name":"Glintons"},{"name":"Golden Grove"},{"name":"Goodwill"},{"name":"Gordon's"},{"name":"Graham's Harbour"},{"name":"Grand Cay"},{"name":"Grays"},{"name":"Great Guana Cay"},{"name":"Green Castle"},{"name":"Green Turtle Cay"},{"name":"Green Turtle Village"},{"name":"Gregory Town"},{"name":"Halls Landing"},{"name":"Harbour Estate"},{"name":"Hard Hill"},{"name":"Harts Bay Hill"},{"name":"Hartswell"},{"name":"Hawks Nest"},{"name":"Hawksbill"},{"name":"Hermitage"},{"name":"Holdiday Track"},{"name":"Holmes Rock"},{"name":"Hope Estate"},{"name":"Hope Town"},{"name":"Hunters"},{"name":"Industrious Hill"},{"name":"James Cistern"},{"name":"Jimmy Hill"},{"name":"John Millars"},{"name":"Kemps Bay"},{"name":"Kemps Point"},{"name":"Killarney"},{"name":"Knowles Village"},{"name":"Landrail Point"},{"name":"Lisbon Creek"},{"name":"Little Bay Settlement"},{"name":"Little Creek"},{"name":"Little Farmers Cay"},{"name":"Long Bay"},{"name":"Love Hill"},{"name":"Love"},{"name":"Lovely Bay"},{"name":"Lowe Sound Settlement"},{"name":"Lower Bogue"},{"name":"Lower Deadman's Cay"},{"name":"Lucaya"},{"name":"Macbride"},{"name":"Majors"},{"name":"Man of War Cay Settlement"},{"name":"Man of War Sound"},{"name":"Mangrove Bush"},{"name":"Mangrove Cay"},{"name":"Markey"},{"name":"Mars Bay"},{"name":"Martin Town"},{"name":"Mastic Point"},{"name":"Mather Town"},{"name":"McKanns"},{"name":"McKenzie"},{"name":"McLeans Town"},{"name":"McQueens"},{"name":"Michelson"},{"name":"Millars"},{"name":"Millers Hill"},{"name":"Millers"},{"name":"Millerton"},{"name":"Minns"},{"name":"Montreal"},{"name":"Morant Bay"},{"name":"Morgan's Bluff"},{"name":"Mortimers"},{"name":"Moss Town"},{"name":"Mount Hope"},{"name":"Mount Pleasant"},{"name":"Mount Thompson"},{"name":"Moxey Town"},{"name":"Murphy Town"},{"name":"Nassau Estate"},{"name":"Nassau"},{"name":"New Bight"},{"name":"New Town"},{"name":"Nicholls Town"},{"name":"Normans Castle"},{"name":"North Cat Cay"},{"name":"North Palmetto Point"},{"name":"Old Bight"},{"name":"Old Grays"},{"name":"Old Place"},{"name":"Orange Creek"},{"name":"Orange Hill"},{"name":"Owens Town"},{"name":"O'Neils"},{"name":"Palmetto Point"},{"name":"Pelican Point"},{"name":"Pigeon Cay"},{"name":"Pinders Point"},{"name":"Pinders"},{"name":"Pine Ridge"},{"name":"Pinefield"},{"name":"Pirates Well"},{"name":"Polly Hill"},{"name":"Pompey Bay"},{"name":"Port Boyd"},{"name":"Port Howe"},{"name":"Port Royal"},{"name":"Pure Gold"},{"name":"Quarters"},{"name":"Rainbow Bay"},{"name":"Ramsey"},{"name":"Reckley Hill"},{"name":"Red Bay Settlement"},{"name":"Richmond Hill"},{"name":"Richmond"},{"name":"Roakers"},{"name":"Roberts Town"},{"name":"Rock Sound"},{"name":"Rokers Point Settlement"},{"name":"Rolletown"},{"name":"Rolleville"},{"name":"Roses"},{"name":"Russell Town"},{"name":"Salina Point"},{"name":"Salt Pond"},{"name":"Sam McKinnons"},{"name":"Sandilands Village"},{"name":"Sandy Point"},{"name":"Savannah Sound"},{"name":"Scrub Hill"},{"name":"Sea Grape"},{"name":"Seaview Settlement"},{"name":"Seminets"},{"name":"Seymour's"},{"name":"Simms"},{"name":"Smith Bay"},{"name":"Smith Point"},{"name":"Smith's Hill"},{"name":"Snake Cay"},{"name":"Snug Corner"},{"name":"South Palmetto Point"},{"name":"South Victoria Hill"},{"name":"Southwest Point"},{"name":"Spring City Settlement"},{"name":"Spring Point"},{"name":"Stafford Creek"},{"name":"Staniard Creek"},{"name":"Stella Maris"},{"name":"Stephenson"},{"name":"Stevens"},{"name":"Steventon"},{"name":"Stuart Manor"},{"name":"Sugar Loaf"},{"name":"Sweeting Cay"},{"name":"Sweetings Village"},{"name":"Taits"},{"name":"Tarpum Bay"},{"name":"Tatnall"},{"name":"Tea Bay"},{"name":"The Bight"},{"name":"The Bluff"},{"name":"The Ferry Settlement"},{"name":"The Lot"},{"name":"The Village"},{"name":"Thomas Town"},{"name":"Thurston Hill"},{"name":"Treasure Cay"},{"name":"Trial Farm"},{"name":"True Blue"},{"name":"Turnbull"},{"name":"Tusculum"},{"name":"Twin Lakes"},{"name":"United Estates"},{"name":"Upper Bogue"},{"name":"Victoria Hill"},{"name":"Victoria Village"},{"name":"Vincent Town"},{"name":"Walker Cay"},{"name":"Water Cay"},{"name":"Waterford"},{"name":"Waterloo"},{"name":"Wemyss Bight"},{"name":"Wemyss"},{"name":"Whitehouse"},{"name":"Williams Town"},{"name":"William's Town"},{"name":"Wilson City"},{"name":"Winton"},{"name":"Wood Cay"},{"name":"Yamacraw Beach Estate"},{"name":"Zion Hill"},{"name":"Zonicles"},{"name":"Abraham's Bay"},{"name":"Alice Town"},{"name":"Arthur's Town"},{"name":"Black Point"},{"name":"Clarence Town"},{"name":"Cockburn Town"},{"name":"Colonel Hill"},{"name":"Duncan Town"},{"name":"Freeport"},{"name":"George Town"},{"name":"Governor's Harbour"},{"name":"Hard Bargain"},{"name":"High Rock"},{"name":"Marsh Harbour"},{"name":"Masons Bay"},{"name":"Matthew Town"},{"name":"Port Nelson"},{"name":"San Andros"},{"name":"Spanish Wells"},{"name":"West End"},{"name":"Belair Estates"},{"name":"Golden Gates Estates"},{"name":"Gun Cay"},{"name":"Highbury Park"},{"name":"Millar Heights"},{"name":"Pinewood Gardens Estate"},{"name":"Sea Breeze Estates"},{"name":"Stapleton Gardens"},{"name":"Winton Heights"},{"name":"Winton Meadows"},{"name":"The Bluff Settlement"},{"name":"Blair Estates"},{"name":"Englerston"},{"name":"Exuma Harbour Estates"},{"name":"Canal Viejo de Bahamas"},{"name":"Nicholas Channel"},{"name":"Palacca Point"},{"name":"Young Sound"},{"name":"Young Island"},{"name":"Yellow Cay"},{"name":"Yellow Bank"},{"name":"Yamacraw Beach"},{"name":"Wreck Bay"},{"name":"Woolendean Cay"},{"name":"Wood Hill"},{"name":"Wood Cay Sound"},{"name":"Wood Cay Point"},{"name":"Wolf Rock"},{"name":"With Low Fall Cay"},{"name":"Witch Point"},{"name":"Windsor Point"},{"name":"Winding Bay"},{"name":"Windermere Island"},{"name":"Wilson Point"},{"name":"Wills Creek"},{"name":"Wills Cay"},{"name":"Williams Island"},{"name":"William's Cay"},{"name":"Wide Opening"},{"name":"White Rock"},{"name":"White Point"},{"name":"White Horses"},{"name":"White Hill Bay"},{"name":"White Cliff"},{"name":"White Cay"},{"name":"White Bluff"},{"name":"White Bay Cay"},{"name":"White Bank"},{"name":"Whale Point"},{"name":"Whale Head"},{"name":"Whale Cay Channel"},{"name":"Whale Cay"},{"name":"Wet Cay"},{"name":"West Shroud Cay"},{"name":"West Point"},{"name":"West Entrance"},{"name":"West End Point"},{"name":"West Cay"},{"name":"West Brother"},{"name":"West Bay"},{"name":"West Barracouta Rock"},{"name":"Well Cay"},{"name":"Wedge Rocks"},{"name":"Wedge Rock"},{"name":"Wedge Point"},{"name":"Wax Cut"},{"name":"Wax Cay Cut"},{"name":"Wax Cay"},{"name":"Water Cays"},{"name":"Washerwoman's Cut"},{"name":"Warren Harbour"},{"name":"Walker's Cay"},{"name":"Walkers Cay"},{"name":"Walker Cay Channel"},{"name":"Walker's Cay Airport"},{"name":"Waderick Wells Cay"},{"name":"Vigilant Cay"},{"name":"Victory Cays"},{"name":"Victoria Lake"},{"name":"Victoria Bay"},{"name":"Veteran Rock"},{"name":"Verde Cay"},{"name":"Upper Wreck Point"},{"name":"Upper Sandy Harbour"},{"name":"Upper Samphire Cay"},{"name":"Upper Point"},{"name":"Upper Cut"},{"name":"Upper Conch Point"},{"name":"Umbrella Cay"},{"name":"Twin Rocks"},{"name":"Twin Cay"},{"name":"Turtle Sound"},{"name":"Turtle Rocks"},{"name":"Turtle Rock"},{"name":"Turtle Reef"},{"name":"Turtle Cove"},{"name":"Turner Sound"},{"name":"Turner Cay"},{"name":"Point Tucker"},{"name":"Triangle Rocks"},{"name":"Cay"},{"name":"Treasure Cay Airport"},{"name":"Top Cay"},{"name":"Tinker Rocks"},{"name":"Timber Creek"},{"name":"Timber Bay"},{"name":"Tilloo Cay"},{"name":"Thunder Channel"},{"name":"Thrift Harbour Creek"},{"name":"Three Sisters Rocks"},{"name":"Thompsons Cay"},{"name":"Thompson Bay"},{"name":"Thomas George Point"},{"name":"Thomas Cay"},{"name":"Thatch Point Sound"},{"name":"Thatch Point"},{"name":"Ten Bay"},{"name":"Tee Cay"},{"name":"Tear Coat Cay"},{"name":"Torzon Cay"},{"name":"Tarpum Head"},{"name":"Symonette Cay"},{"name":"Sweetings Pond"},{"name":"Sumner Point"},{"name":"Sugar Rock"},{"name":"Sugar Loaf Cay"},{"name":"Sugar Bay"},{"name":"Strangers Cay Rocks"},{"name":"Strangers Cay Channel"},{"name":"Strangers Cay"},{"name":"Stranger Cay Banks"},{"name":"Strachan Cay"},{"name":"Storr's Lake"},{"name":"Stoney Cay"},{"name":"Stocking Island"},{"name":"Stella Maris Airport"},{"name":"Steamer Cay"},{"name":"Statira Shoal"},{"name":"Staniel Cay"},{"name":"Staniel Cay Airport"},{"name":"Staniard Rock"},{"name":"Square Rocks"},{"name":"Springfield Bay"},{"name":"Spencers Bight"},{"name":"Spar Creek"},{"name":"Spanish Cay"},{"name":"Spanish Cay Airport"},{"name":"Southwest Reef"},{"name":"South West Reef"},{"name":"South West Point"},{"name":"South West Bay"},{"name":"South Stirrup Cay"},{"name":"Southside Bay"},{"name":"South Sail Rock"},{"name":"South Rocks"},{"name":"South Rock"},{"name":"South Riding Rock"},{"name":"South Point"},{"name":"South Mangrove"},{"name":"South Head"},{"name":"South Hall's Spot"},{"name":"Southern End Point"},{"name":"Southern Cay"},{"name":"South Bight"},{"name":"Cape Verde"},{"name":"South East Point"},{"name":"Southeast Point"},{"name":"Southeast Cay"},{"name":"South Dog"},{"name":"South Channel Cay"},{"name":"South Cay"},{"name":"South Cat Cay"},{"name":"South Bluff"},{"name":"South Bimini"},{"name":"South Beach"},{"name":"South Bay"},{"name":"Southampton Reef"},{"name":"Sound Point"},{"name":"Somerset Creek"},{"name":"Soldier Cays"},{"name":"Soldier Cay"},{"name":"Snow Bay"},{"name":"Snapper Cay"},{"name":"Snap Hill"},{"name":"Smith Sloop Point"},{"name":"Smith Cay"},{"name":"S & M Farm"},{"name":"Slaughter Harbour"},{"name":"Six Shilling Cays"},{"name":"Sisters Rocks"},{"name":"Sister Rocks"},{"name":"Sisters Cays"},{"name":"Sinky Bay"},{"name":"Simon Creek"},{"name":"Point Simon"},{"name":"Simms Point"},{"name":"Silver Point"},{"name":"Silver Cay"},{"name":"Shroud Cays"},{"name":"Shroud Cay"},{"name":"Ship Channel Cay"},{"name":"Ship Channel"},{"name":"Sheep Cay"},{"name":"Sharp Rocks Point"},{"name":"Sharp Rock Point"},{"name":"Shark Spit"},{"name":"Shamrock Bay"},{"name":"Shallow Water Point"},{"name":"S.E. Sand Rock"},{"name":"Seal Cay"},{"name":"Scrub Cays"},{"name":"Scrubby Hill"},{"name":"Scott Rocks"},{"name":"Scotland Cay"},{"name":"Scotland Cay Airport"},{"name":"Scorpion Cay"},{"name":"Scopley Rock"},{"name":"Schooner Cays"},{"name":"Sawyer Bluff"},{"name":"Saunder's Beach"},{"name":"Sapodilla Creek"},{"name":"Sapodilla Cay"},{"name":"Cay Santo Domingo"},{"name":"Santaren Channel"},{"name":"Cape Santa Maria"},{"name":"San Salvador Island"},{"name":"San Salvador District"},{"name":"Sandy Point District"},{"name":"Sandy Point Airport"},{"name":"Sandy Harbour"},{"name":"Sandy Creek"},{"name":"Sandy Cay"},{"name":"Sandy Bay"},{"name":"Sandy Banks Bay"},{"name":"Sand Ridge Sound"},{"name":"Sanders Island"},{"name":"Sand Bank Cays"},{"name":"San Andros Airport"},{"name":"Sampson Cay"},{"name":"Samphire Cays"},{"name":"Samphire Cay"},{"name":"Samana Cay"},{"name":"Samana Cays"},{"name":"Salvador Point"},{"name":"Salt Pond Point"},{"name":"Saltpond Hill"},{"name":"Salt Pond Cay"},{"name":"Salt Cay Anchorage"},{"name":"Salt Cay"},{"name":"Sale Cay Rocks"},{"name":"Cay Sal"},{"name":"Saint Vincent Rock"},{"name":"Saint Georges Island"},{"name":"Saint George Bay"},{"name":"Sail Rocks"},{"name":"Sail Rock"},{"name":"Sailor's Choice"},{"name":"Saddle Cay"},{"name":"Saddleback Cay"},{"name":"Saddle Back Cay"},{"name":"Russells Bay"},{"name":"Russel Island"},{"name":"Russel Baldwin Rock"},{"name":"Rum Cay"},{"name":"Rum Cay Island"},{"name":"Rudder Cut Cay"},{"name":"Rudder Cut"},{"name":"Rudder Cut Cay Airport"},{"name":"Royal Island"},{"name":"Round Rock"},{"name":"Round Cay"},{"name":"Round Bush"},{"name":"Rose Rock"},{"name":"Rose Island Rocks"},{"name":"Rose Island"},{"name":"Lake Rosa"},{"name":"Rompidas"},{"name":"Roker Cay"},{"name":"Rocky Point"},{"name":"Rocky Harbour"},{"name":"Rocky Crossing"},{"name":"Rock Sound International Airport"},{"name":"Rock Sound District"},{"name":"Rock Point"},{"name":"Rock Harbour Cays"},{"name":"Riding Rocks"},{"name":"Riding Rock Point"},{"name":"Riding Point"},{"name":"Rhoda Rocks"},{"name":"Reserve Bay"},{"name":"Relief Bay"},{"name":"Reids Cay"},{"name":"Red Shank Cay"},{"name":"Red Hole"},{"name":"Red Bay"},{"name":"Ratman Cays"},{"name":"Rat Cay"},{"name":"Rat and Goat Cays"},{"name":"Randall's Cay"},{"name":"Raineys Point"},{"name":"Ragged Island Range"},{"name":"Ragged Island Harbour"},{"name":"Ragged Island District"},{"name":"Ragged Island"},{"name":"Racoon Cut"},{"name":"Raccoon Cay"},{"name":"Quintus Rocks"},{"name":"Queen's Cove"},{"name":"Queens Channel"},{"name":"Pye's Harbour"},{"name":"Pye Point"},{"name":"Pumpion Lake"},{"name":"Pumpion Cay"},{"name":"Pull and be Damned"},{"name":"Pudding Cut"},{"name":"Powell Point"},{"name":"Powell Cay"},{"name":"Potter Cay"},{"name":"Pots Rocks"},{"name":"Pot Cay"},{"name":"Portland Harbour"},{"name":"Porpoise Creek"},{"name":"Pork Fish Rocks"},{"name":"Porgee Rocks"},{"name":"Pond Bay"},{"name":"Pompey Rocks"},{"name":"Pompey Creek"},{"name":"Poison Point"},{"name":"Plum Cays"},{"name":"Pleasant Bay"},{"name":"Plana Cays"},{"name":"Mount Pisgah"},{"name":"Pirates Well Pond"},{"name":"Piquet Rocks"},{"name":"Pipe Cay"},{"name":"Pine Tree Cay"},{"name":"Pinefield Point"},{"name":"Pine Cay"},{"name":"Pinder Point"},{"name":"Pimlico Rocks"},{"name":"Pimlico Islands"},{"name":"Pimlico Cays"},{"name":"Pigeon Island"},{"name":"Pigeon Cays"},{"name":"Pierre Island"},{"name":"Pierre Reef"},{"name":"Petit Cay"},{"name":"Peterson Cay"},{"name":"Perry Rock"},{"name":"Perpall's Cay"},{"name":"Periwinkle Rock"},{"name":"Pensacola Cays"},{"name":"Pelican Harbour"},{"name":"Pelican Creek"},{"name":"Pelican Cays"},{"name":"Pelican Cay"},{"name":"Pee Wee Point"},{"name":"Pearson Cay"},{"name":"Pear Cay"},{"name":"Pawpaw Rocks"},{"name":"Pawpaw Cays"},{"name":"Paw Paw Cay"},{"name":"Patton Cays"},{"name":"Parrot Cays"},{"name":"Paradise Point"},{"name":"Paradise Island"},{"name":"Palacca Bight"},{"name":"Oyster Cay"},{"name":"Over Yonder Cay"},{"name":"Outer Point Cay"},{"name":"Oree Bay"},{"name":"Orange Creek Point"},{"name":"Orange Cay"},{"name":"Old Yankee Land"},{"name":"Old Jean's Bay"},{"name":"Old House Point"},{"name":"Old Fort Point"},{"name":"Old Fort Bay"},{"name":"Old Culmers Point"},{"name":"Old Bight Landing"},{"name":"Okra Cross Point"},{"name":"Ocean Point"},{"name":"Ocean Cay"},{"name":"Ocean Bight"},{"name":"O'Brien Cay"},{"name":"Oakes Field-Nassau Heliport"},{"name":"Nurse Spit"},{"name":"Nurse Channel"},{"name":"Nurse Cay"},{"name":"Nunjack Channel"},{"name":"Nun Jack Cay"},{"name":"Nuevitas Rocks"},{"name":"Noss Mangrove"},{"name":"Northwest Providence Channel"},{"name":"Northwest Point"},{"name":"North West Point"},{"name":"North West Harbour"},{"name":"Northwest Channel"},{"name":"Northwest Cay"},{"name":"North Shore"},{"name":"North Rock"},{"name":"North Hall's Spot"},{"name":"Northern Eleuthera Island"},{"name":"North Eleuthera Airport"},{"name":"North Bight"},{"name":"North End Point"},{"name":"North End"},{"name":"North East Rock"},{"name":"Northeast Rock"},{"name":"Northeast Providence Channel"},{"name":"North East Point"},{"name":"Northeast Point"},{"name":"North East Breaker"},{"name":"North Dog"},{"name":"North Channel Cay"},{"name":"North Cay"},{"name":"North Bimini"},{"name":"North Beach"},{"name":"North Bar Channel"},{"name":"Norman's Pond Cay"},{"name":"Norman Spit"},{"name":"Norman's Cay Island"},{"name":"Norman's Cay Airport"},{"name":"No Name Cay"},{"name":"No Bush Cay"},{"name":"Noah Bethel Cays"},{"name":"Nixon's Harbour"},{"name":"Nigh Creek"},{"name":"Berry Islands District"},{"name":"New Zealand Point"},{"name":"Newtown Cay"},{"name":"New Providence"},{"name":"New Providence District"},{"name":"New Found Harbour"},{"name":"New Cay"},{"name":"New Bight Airport"},{"name":"Nesbitt Point"},{"name":"Lynden Pindling International Airport"},{"name":"Nassau Harbour"},{"name":"Mutton Fish Point"},{"name":"Musha Cay"},{"name":"Munnings Knoll"},{"name":"Muertos Cays"},{"name":"Mudian Harbour"},{"name":"Muddy Point"},{"name":"Mucaras Reef"},{"name":"Mouth of Harbour Cay"},{"name":"Mount View"},{"name":"Mount Pleasant Point"},{"name":"Mount Creek"},{"name":"Moselle Bank"},{"name":"Mortimers Hill"},{"name":"Moriah Harbour Cay"},{"name":"Morgan Bluff"},{"name":"Moraine Cay Channel"},{"name":"Moraine Cay"},{"name":"Moore's Island"},{"name":"Fort Montague"},{"name":"Montagu Bay"},{"name":"Money Point"},{"name":"Money Cay"},{"name":"Mitchell Creek"},{"name":"Mount Misery"},{"name":"Mira Por Vos Passage"},{"name":"Mira Por Vos"},{"name":"Miller Creek"},{"name":"Millars Sound"},{"name":"Middle Isaac"},{"name":"Middle Ground"},{"name":"Middle Cay"},{"name":"Middle Bight Cay"},{"name":"Middle Bight"},{"name":"Memory Rock"},{"name":"Meleta Cay"},{"name":"Meeks Patch"},{"name":"McKay's Bluff"},{"name":"Maycock Cay"},{"name":"Mayaguana Passage"},{"name":"Mayaguana"},{"name":"Mayaguana District"},{"name":"Matt Lowe's Cay"},{"name":"Mattis Point"},{"name":"Matanilla Shoal"},{"name":"Matanilla Reef"},{"name":"Mastic Cay"},{"name":"Mastic Bay"},{"name":"Mason Bay"},{"name":"Marsh Harbour District"},{"name":"The Marls"},{"name":"Market Fish Cays"},{"name":"Market Fish Cay"},{"name":"Marions Bluff"},{"name":"Maria Bay"},{"name":"Margaret Cay"},{"name":"Man o' War Point"},{"name":"Man of War Cay"},{"name":"Man o' War Cay"},{"name":"Man-of-War Channel"},{"name":"Man of War Channel"},{"name":"Man of War Cays"},{"name":"Man-of-War Cay"},{"name":"Man-of-War Bush"},{"name":"Man of War Bay"},{"name":"Man Island"},{"name":"Man Head Cay"},{"name":"Mangrove Rocks"},{"name":"Mangrove Point"},{"name":"Mangrove Island"},{"name":"Mangrove Cove"},{"name":"Mangrove Cay Island"},{"name":"Clarence A. Bain Airport"},{"name":"Mama Rhoda Rock"},{"name":"Malcolm Creek"},{"name":"Big Major's Spot"},{"name":"Major Rocks"},{"name":"Major's Cay Harbour"},{"name":"Magallanes Bank"},{"name":"Madioca Point"},{"name":"Madiera Cay"},{"name":"Madam Dau's Cay"},{"name":"Mackie Shoal"},{"name":"Mackie Bank"},{"name":"Mackerel Point"},{"name":"Lynyard Cay"},{"name":"Lyford Cay"},{"name":"Lydia Point"},{"name":"Lucretia Point"},{"name":"Lucian Cay"},{"name":"Lucaya Estates"},{"name":"Lubbers Quarters"},{"name":"Low Water Harbour Cay"},{"name":"Low Rocks"},{"name":"Low Rock"},{"name":"Low Point Hill"},{"name":"Low Point"},{"name":"Lowe Sound"},{"name":"Lower Wreck Point"},{"name":"Lower Crisby Swash"},{"name":"Lower Chub Point"},{"name":"Low Cay"},{"name":"Low Born Cay"},{"name":"Lovely Bay Cays"},{"name":"Love Beach"},{"name":"Louis Town"},{"name":"Long Rocks"},{"name":"Long Rock"},{"name":"Long Pond"},{"name":"Long Point"},{"name":"Big Mangrove"},{"name":"Long Island"},{"name":"Long Cay"},{"name":"Long Bay Field Point"},{"name":"Long Bay Cays"},{"name":"Lone Pine Cay"},{"name":"London Creek"},{"name":"Loggerhead Point"},{"name":"Loggerhead Creek"},{"name":"Lockhart Cay"},{"name":"Lobster Cays"},{"name":"Lobster Cay"},{"name":"Cay Lobos"},{"name":"Loafers Seat"},{"name":"Lloyd Rock"},{"name":"Little Whale Cay"},{"name":"Little Wax Cay"},{"name":"Little Walker Cay"},{"name":"Little Stirrup Cay"},{"name":"Little San Salvador"},{"name":"Little Sale Cay"},{"name":"Little Romers Cay"},{"name":"Little Ragged Island"},{"name":"Little Pimlico Island"},{"name":"Little Petit Cay"},{"name":"Little Nurse Cay"},{"name":"Little Meeks Patch Island"},{"name":"Little Major's Spot"},{"name":"Little Loggerhead Creek"},{"name":"Little Lloyd Cay"},{"name":"Little Lake"},{"name":"Little Joe Downer Cay"},{"name":"Little Isaac"},{"name":"Little Inagua"},{"name":"Little High Cay"},{"name":"Little Harbour Cay"},{"name":"Little Harbour Bay"},{"name":"Little Harbour"},{"name":"Little Grassy Creek"},{"name":"Little Grand Cay"},{"name":"Little Farmer's Cay"},{"name":"Little Exuma"},{"name":"Little Egg Island"},{"name":"Little Darby Island"},{"name":"Little Crab Cay"},{"name":"Little Cistern Cay"},{"name":"Little Cay"},{"name":"Little Cave Cay"},{"name":"Little Carters Cay"},{"name":"Little Bersus Cay"},{"name":"Little Bell Island"},{"name":"Little Bay"},{"name":"Little Abaco"},{"name":"Linder Cay"},{"name":"Lime Pond"},{"name":"Lily Bank"},{"name":"Lilly Cay"},{"name":"Lignumvitae Cay"},{"name":"Lightbourn's Cay"},{"name":"Lightbourn Creek"},{"name":"Liberty Rock"},{"name":"Levi Island"},{"name":"Lee Stocking Island"},{"name":"River Lees"},{"name":"Lavenderas Rocks"},{"name":"Laughing Bird Cay"},{"name":"Larks Nest"},{"name":"Lark Channel"},{"name":"Large Hole"},{"name":"Lanzadera Cay"},{"name":"Lanthorn Head"},{"name":"Lantern Head Harbour"},{"name":"Lantern Head"},{"name":"Labanderas Reef"},{"name":"Krall Creek"},{"name":"Kits Cay"},{"name":"Killura Poly Rock"},{"name":"Lake Killarney"},{"name":"Kidds Cove"},{"name":"Keir Mount"},{"name":"Kemps Bay District"},{"name":"Kemp Cay"},{"name":"Junker's Landing"},{"name":"Junkanoo Rock"},{"name":"Jump Off Rock"},{"name":"Jumentos Cays"},{"name":"Joulter Cays"},{"name":"Josephs Cay"},{"name":"Johnson Cay"},{"name":"Johnny's Cay"},{"name":"John Creek"},{"name":"John Cash Point"},{"name":"Joe Downer Cay"},{"name":"Joe Creek"},{"name":"Joe Cays"},{"name":"Joe Cay"},{"name":"Jim Point"},{"name":"Jim Hunt Bay"},{"name":"Jewfish Cay"},{"name":"James Point"},{"name":"James Hill"},{"name":"James Cay"},{"name":"Jamaica Well Point"},{"name":"Jamaica Spit"},{"name":"Jamaica Cay"},{"name":"Jamaica Bay"},{"name":"Jacobs Island"},{"name":"Jacob Cay"},{"name":"Jacks Bluff"},{"name":"Jack Fish Channel"},{"name":"Israel Creek"},{"name":"Iron Cay"},{"name":"Inner Point"},{"name":"Indian Hole"},{"name":"Indian Head Point"},{"name":"Indian Cay"},{"name":"Inagua Airport"},{"name":"Inagua"},{"name":"Iguana Cay"},{"name":"Hut Point"},{"name":"Hurricane Hole"},{"name":"Hurricane Flats"},{"name":"Hose Point"},{"name":"Horsewell Bay"},{"name":"Horse Pond Bay"},{"name":"Horse Pond"},{"name":"Holm Cays"},{"name":"Hole in the Wall Anchorage"},{"name":"Hogsty Reef"},{"name":"Hog Point"},{"name":"Hog Cays"},{"name":"Hog Cay Airstrip"},{"name":"Hog Cay/Little Exuma Island"},{"name":"Hog Cay Cut"},{"name":"Hog Cay"},{"name":"Hoffman Cay"},{"name":"Hobson Breaker"},{"name":"Hinchinbroke Rocks"},{"name":"Hills Cay"},{"name":"High Rock District"},{"name":"High Ridge Cay"},{"name":"High Point Cay"},{"name":"High Point"},{"name":"High Cay"},{"name":"Highborne Cut"},{"name":"Highbourn Cay"},{"name":"High Banks Bay"},{"name":"High Bank Bay"},{"name":"Hen and Chicken Rocks"},{"name":"Hell Gate"},{"name":"Heastie Bay"},{"name":"Head of Harbour"},{"name":"Hawks Nest Point"},{"name":"Hawksbill Creek"},{"name":"Hawks Nest Airport"},{"name":"Hawksnest Cay"},{"name":"Hawk's Nest Cay"},{"name":"Hawksbill Rock"},{"name":"Hawks Bill Hill"},{"name":"Hawksbill Cays"},{"name":"Hawksbill Cay"},{"name":"Hawk Point"},{"name":"Hawk Creek"},{"name":"Hatchet Point"},{"name":"Harvey Cay"},{"name":"Harveys Bay"},{"name":"Harry Point"},{"name":"Harold Pond"},{"name":"Harbour Island District"},{"name":"Harbour Island"},{"name":"Hanover Sound"},{"name":"Halls Pond Cay"},{"name":"Hall's Point"},{"name":"Halfway Rock"},{"name":"Haines Channel"},{"name":"Haines Cay"},{"name":"Haines Bluff"},{"name":"Gut Island"},{"name":"Gun Point"},{"name":"Gun Bluff"},{"name":"Guinea Schooner Bay"},{"name":"Guinchos Cay"},{"name":"Guano Point"},{"name":"Guano Cay"},{"name":"Guana Cay"},{"name":"Grunt Cay"},{"name":"Grouper Rocks"},{"name":"Ground Corn Point"},{"name":"Grindstone Point"},{"name":"Griffins Cay"},{"name":"Green Turtle Cay District"},{"name":"Green's Harbour"},{"name":"Green Cay"},{"name":"Green Bush"},{"name":"Great Stirrup Cay"},{"name":"Great Salt Pond"},{"name":"Great Sale Cay"},{"name":"Porpoise Rocks"},{"name":"Great Lake"},{"name":"Great Isaac"},{"name":"Great Inagua"},{"name":"Great Harbour Cay Airport"},{"name":"Great Harbour Cay"},{"name":"Great Harbour"},{"name":"Great Exuma"},{"name":"Great Cay"},{"name":"Great Bersus Cay"},{"name":"Grassy Creek Cays"},{"name":"Grassy Creek"},{"name":"Grape Tree"},{"name":"Grape Point"},{"name":"Granny Lake"},{"name":"Grand Pa's Channel"},{"name":"Grand Lucayan Waterway"},{"name":"Grand Cays"},{"name":"Grand Bahama Island"},{"name":"Grand Bahama Auxiliary Air Force"},{"name":"Governor's Harbour District (historical)"},{"name":"Goulding Cay"},{"name":"Gordon Bluff"},{"name":"Gorda Rock"},{"name":"Gorda Cay"},{"name":"Goose River"},{"name":"Goole Cay"},{"name":"Goodman Bay"},{"name":"Good Hope Pond"},{"name":"Gold Rock Creek"},{"name":"Gold Rock"},{"name":"Golding Cays"},{"name":"Golding Cay"},{"name":"Golden Rock"},{"name":"Goat Cay"},{"name":"Glenton Sound"},{"name":"Glass Window"},{"name":"Glass Cay"},{"name":"Gingerbread Ground"},{"name":"Gilpin Point"},{"name":"Gilpin Bay"},{"name":"Gibson Cay"},{"name":"Georgetown Harbour"},{"name":"Lake George"},{"name":"Gaulin Cay"},{"name":"Gaulding Cay"},{"name":"Garden Cay"},{"name":"Galliot Cut"},{"name":"Galliot Cay"},{"name":"Galliot Bank"},{"name":"Fresh Creek District"},{"name":"Fresh Creek"},{"name":"French Bay"},{"name":"Grand Bahama International Airport"},{"name":"Freeport Harbour"},{"name":"City of Freeport District"},{"name":"Frazer's Hog Cay"},{"name":"Frankfort Point"},{"name":"Fowl Cay"},{"name":"Foots Cay"},{"name":"Fleeming Point"},{"name":"Fleeming Channel"},{"name":"Flamingo Pond"},{"name":"Flamingo Point"},{"name":"Flamingo Cay"},{"name":"Fish Rocks"},{"name":"Fish Point"},{"name":"Fishing Cays"},{"name":"Fish Hawk Cay"},{"name":"Fish Cays"},{"name":"Fish Cay"},{"name":"Finley Cay"},{"name":"Fine Bay"},{"name":"Fort Fincastle"},{"name":"Fifteen Foot Cay"},{"name":"Fiddle Cay"},{"name":"Fernandez Cay"},{"name":"Fernandez Bay"},{"name":"Ferguson Point"},{"name":"Fat Turtle Sound"},{"name":"Farmers Cay Cut"},{"name":"Far Creek"},{"name":"Fanny Cay"},{"name":"Fanny Bay"},{"name":"Exuma Sound"},{"name":"Exuma Harbour"},{"name":"Exuma District"},{"name":"Exuma Cays Land and Sea Park"},{"name":"Exuma Cays"},{"name":"Exuma Bank"},{"name":"Entrance Point"},{"name":"Elizabeth Island"},{"name":"Elizabeth Harbour"},{"name":"Eleuthera Island"},{"name":"Cape Eleuthera"},{"name":"Elbow Cays"},{"name":"Elbow Cay"},{"name":"Elbow Bank"},{"name":"Eight Mile Rock Bay"},{"name":"Eight Mile Bay"},{"name":"Egg Reef"},{"name":"Egg Island"},{"name":"East Wells"},{"name":"East Reef"},{"name":"East Isaac"},{"name":"East Hill"},{"name":"Eastern Point"},{"name":"Eastern Channel"},{"name":"Eastern Bay"},{"name":"East Entrance"},{"name":"East End Point"},{"name":"East Brother"},{"name":"East Barracouta Rock"},{"name":"Eagle Rock"},{"name":"Dundee Bay"},{"name":"Dunc Cays"},{"name":"Duncanson Point"},{"name":"Duncan Point"},{"name":"Duck Cays"},{"name":"Duck Cay"},{"name":"Dry Cay"},{"name":"Dove Cay"},{"name":"Douglas Road"},{"name":"Douglas Channel"},{"name":"Double Headed Shot Cays"},{"name":"Double Breaster Cays"},{"name":"Double Breaster Bars"},{"name":"Double Breasted Cay"},{"name":"Double Bay"},{"name":"Dont Rock"},{"name":"Dolly's Cut"},{"name":"Dolly Cay"},{"name":"Dollar Harbour"},{"name":"Dog Rocks"},{"name":"Dog Head Point"},{"name":"Dilly Cay"},{"name":"Dicks Point"},{"name":"Dickies Cay"},{"name":"Diana Bank"},{"name":"Diamond Point"},{"name":"Diamond Crystal"},{"name":"Diamond Cay"},{"name":"Devils Point"},{"name":"Devils Cay"},{"name":"Delectable Bay"},{"name":"Delaport Point"},{"name":"Delaport Bay"},{"name":"Deep Water Cay"},{"name":"Deans Bay"},{"name":"Deals Point"},{"name":"Deals Creek"},{"name":"Deadman's Reef Point"},{"name":"Deadmans Reef"},{"name":"Dead Mans Bay"},{"name":"Upper Channel Cay"},{"name":"Davis Point"},{"name":"Datum Bay"},{"name":"Darville Cay"},{"name":"Darby Island"},{"name":"Daniels Cay"},{"name":"Dangerous Shoals"},{"name":"Danger Cay"},{"name":"Damas Cays"},{"name":"Cutlass Bay Airport"},{"name":"Cut Cay"},{"name":"Curtis Creek"},{"name":"Curry Mury Point"},{"name":"Current Rock"},{"name":"Current Island"},{"name":"Current Cut"},{"name":"Curley Cut Cays"},{"name":"Cupids Cay"},{"name":"Lake Cunningham"},{"name":"Culmer's Cay"},{"name":"Culberts Point"},{"name":"Culberts Bay"},{"name":"Crown Point"},{"name":"Crow Hill"},{"name":"Crossing Rock Bay"},{"name":"Cross Harbour Point"},{"name":"Cross Harbour Creek"},{"name":"Cross Harbour"},{"name":"Cross Cays"},{"name":"Cross Cay"},{"name":"Cross Bay"},{"name":"Crooked Island Passage"},{"name":"Crooked Island"},{"name":"Colonel Hill Airport"},{"name":"Cristophe Point"},{"name":"Crisby Swash"},{"name":"Creek Point"},{"name":"Crab Rock"},{"name":"Crab Cay"},{"name":"Cow and Bull"},{"name":"Covery Bight"},{"name":"Cove Point"},{"name":"Coventry Bight"},{"name":"Cotton Point"},{"name":"Cotton Field Point"},{"name":"Cotton Cay"},{"name":"Corry Sound"},{"name":"Cornwall Point"},{"name":"Cornish Cay"},{"name":"Cormorant Point"},{"name":"Cormorant Cay"},{"name":"Copper Rock"},{"name":"Cook's Cay"},{"name":"South Andros Airport"},{"name":"Conch Spit"},{"name":"Conch Sound"},{"name":"Conch Shell Point"},{"name":"Conchshell Cay"},{"name":"Conch Rocks"},{"name":"Conch Cut"},{"name":"Conch Cay"},{"name":"Conception Island"},{"name":"Compass Cay"},{"name":"Comfort Cay"},{"name":"Columbus Point"},{"name":"Columbus Bank"},{"name":"Coconut Point"},{"name":"Coco Cay"},{"name":"Coco Bay"},{"name":"Cocoa Plum Cay"},{"name":"Cockroach Cay"},{"name":"Cochinos Banks"},{"name":"Coal Bay"},{"name":"Coakley Cay"},{"name":"Cluffs Cay"},{"name":"Clifton Point"},{"name":"Clifton Bluff"},{"name":"Clem Cay"},{"name":"Clarion Bank"},{"name":"Claret Cove"},{"name":"Cistern Point"},{"name":"Cistern Cay"},{"name":"Cistern Field"},{"name":"Icely Rock"},{"name":"Chub Rock"},{"name":"Chub Cay International Airport"},{"name":"Chubb Rocks"},{"name":"China Hill"},{"name":"Chim Pond"},{"name":"Cherokee Point"},{"name":"Chatham Rocks"},{"name":"Fort Charlotte"},{"name":"Channel Rocks"},{"name":"Channel Rock"},{"name":"Channel Cays"},{"name":"Channel Cay"},{"name":"Chalk Sound"},{"name":"Cecil Rocks"},{"name":"Cays to Eleuthera"},{"name":"Cay Point"},{"name":"The Cay"},{"name":"Cave Point"},{"name":"Big Cave Cay"},{"name":"Cave Cay"},{"name":"Catto Cay"},{"name":"Cat Island"},{"name":"Catch Island"},{"name":"Cat Cays"},{"name":"Cat Cay"},{"name":"Castle Rock"},{"name":"Castle Island"},{"name":"Cashs Cay"},{"name":"Carter's Cays"},{"name":"Carrion Crow Harbour"},{"name":"Carmichael"},{"name":"Canfield Bay"},{"name":"Camp Bang Bang"},{"name":"Calm Cove"},{"name":"California Sound"},{"name":"Calcutta Creek"},{"name":"Calabash Cay"},{"name":"Caicos Passage"},{"name":"Caeser Cay"},{"name":"Cable Beach"},{"name":"Cabbage Cay"},{"name":"Bushes"},{"name":"Burrows Harbour"},{"name":"Burnside Cove"},{"name":"Burnside Cay"},{"name":"Bullets Hill"},{"name":"Bonavista Cay"},{"name":"Buckley's Point"},{"name":"Buckle Cut"},{"name":"Brush Cays"},{"name":"Brush Cay"},{"name":"Browns Point"},{"name":"Browns Channel"},{"name":"Brown Cay"},{"name":"Brown Bank"},{"name":"The Brothers"},{"name":"Broth Cay"},{"name":"Broken Bay"},{"name":"Bristol Galley"},{"name":"Brigantine Cays"},{"name":"Bridges Cay"},{"name":"Bridge Point"},{"name":"Brets Hill"},{"name":"Breezy Point"},{"name":"Braudie Point"},{"name":"Bowe's Sound"},{"name":"Bowe Cay"},{"name":"Bootle Bay Point"},{"name":"Bootle Bay"},{"name":"Booby Rocks"},{"name":"Booby Cay"},{"name":"Bonefish Pond"},{"name":"Bonefish Point"},{"name":"Bonefish Cay"},{"name":"Bonefish Bay"},{"name":"Bonds Cay"},{"name":"Bock Cay"},{"name":"Bob's Nose"},{"name":"Bob Cay"},{"name":"Boat Rock"},{"name":"Boat Harbour Point"},{"name":"Boat Harbour"},{"name":"Boat Channel"},{"name":"Boar Hog Point"},{"name":"Bluff Cay"},{"name":"Bluff"},{"name":"Blue Hole"},{"name":"Blue Hills"},{"name":"Blossom Channel"},{"name":"Blackwood Point"},{"name":"Black Wood Point"},{"name":"Blackwood Bush"},{"name":"Blacksmith Landing"},{"name":"Black Rocks"},{"name":"Black Rock Point"},{"name":"Black Rock"},{"name":"Black Point Hill"},{"name":"Bitter Guana Cay"},{"name":"Bird Rock"},{"name":"Bird Point"},{"name":"Bird Cay"},{"name":"Bimini Islands"},{"name":"Bimini District"},{"name":"Gold Cay"},{"name":"Big Wood Cay"},{"name":"Big Wood"},{"name":"Big Whale Cay"},{"name":"Big Thrift Harbour Cay"},{"name":"Big Romers Cay"},{"name":"Big Rock Cut"},{"name":"Big Pond Lake"},{"name":"Big Pond"},{"name":"Big Pigeon Cay"},{"name":"Big Pelican"},{"name":"Big Lloyd Cay"},{"name":"Big Lake Cay"},{"name":"Big Joe Downer Cay"},{"name":"Big Jerry Cay"},{"name":"Bight Point"},{"name":"Big Hog Cay"},{"name":"Bighead Cay"},{"name":"Big Harbour Cay"},{"name":"Big Grand Cay"},{"name":"Big Farmer's Cay"},{"name":"Great Egg Island"},{"name":"Big Cross Cay"},{"name":"Big Crab Cay"},{"name":"Big Cay"},{"name":"Big Carters Cay"},{"name":"Big Bluff"},{"name":"Bethel Channel"},{"name":"Berry Islands"},{"name":"Ben's Landing"},{"name":"Ben Bluff"},{"name":"Bell Island"},{"name":"Beak Cay"},{"name":"Beacon Cay"},{"name":"Bay Pond"},{"name":"Bassett Cove"},{"name":"Basil Rock"},{"name":"Base Line Cay"},{"name":"Barren Rock"},{"name":"Barracuda Swash"},{"name":"Barracouta Rocks Channel"},{"name":"Barracouta Rocks"},{"name":"Barracouta Banks"},{"name":"Barn Cay"},{"name":"Barker's Point"},{"name":"Barra Terre"},{"name":"Bamboo Point"},{"name":"Bamboo Cay"},{"name":"Bakers Bluff"},{"name":"Bains Bluff"},{"name":"Bahamas National Trust Park"},{"name":"Commonwealth of The Bahamas"},{"name":"Bahama Islands"},{"name":"Bacchus Rock"},{"name":"August Cay"},{"name":"Atwood Harbour"},{"name":"Atwood Creek"},{"name":"Athol Island"},{"name":"Arvida Bay"},{"name":"Arthur's Town Airport"},{"name":"Archers Cay"},{"name":"Arawak Cay"},{"name":"Anna Cay"},{"name":"Anguilla Cays"},{"name":"Angel Fish Point"},{"name":"Angel Cays"},{"name":"Andros Town International Airport"},{"name":"Andros Island"},{"name":"Andros Central"},{"name":"Anderson Cay"},{"name":"Ambergris Cays"},{"name":"Ambergris Cay"},{"name":"Mount Alvernia"},{"name":"Allan Cay"},{"name":"Alligator Point"},{"name":"Alligator Bay"},{"name":"Allen Cays"},{"name":"Alfred Sound"},{"name":"Alder Cay"},{"name":"Alboy Hole"},{"name":"Adeline Cay"},{"name":"Adelaide Beach"},{"name":"Adderley Cay"},{"name":"Acklins"},{"name":"Acklins Island District"},{"name":"Bight of Acklins"},{"name":"Abraham Bay"},{"name":"Abraham Creek"},{"name":"Abraham Hill"},{"name":"Abner Cay"},{"name":"Abaco Island"},{"name":"Cay Sal Bank"},{"name":"Middle Knoll"},{"name":"Knife Cay"},{"name":"Frog Cay"},{"name":"Sister Cays"},{"name":"Upper Ending Point"},{"name":"Riding Point Terminal"},{"name":"Bell Channel"},{"name":"Pinder Point Shoal"},{"name":"Henry Bank"},{"name":"North Turtle Rock"},{"name":"Barnett Harbour"},{"name":"Grassy Bay"},{"name":"Moxon Rocks"},{"name":"Rabbit Rock"},{"name":"Cat Point"},{"name":"Ocean Cay Terminal"},{"name":"Duck Lake"},{"name":"Marion Rock"},{"name":"Nairn Cay"},{"name":"Ben Cay"},{"name":"Johnson Spit"},{"name":"Twin Cays"},{"name":"Loggerhead Cay"},{"name":"Jew Fish Rock"},{"name":"Bacchus Point"},{"name":"Blackbeard Rocks"},{"name":"Blackbeard Bay"},{"name":"Limestone Bluff"},{"name":"Peak Rock"},{"name":"Table Rock"},{"name":"Lovers Leap"},{"name":"South Side Hill"},{"name":"East Rock"},{"name":"Toney Rock"},{"name":"Pear Cay Pass"},{"name":"West Comer Rock"},{"name":"Comer Rock"},{"name":"Stephenson Rock"},{"name":"Little Turtle"},{"name":"North Channel Rocks"},{"name":"Allen Cay"},{"name":"Cave Cay Cut"},{"name":"Tartar Bank"},{"name":"Dolphin Head Bluff"},{"name":"Sand Point"},{"name":"Miller Anchorage"},{"name":"Deep Hole"},{"name":"Pineapple Cays"},{"name":"Lochaber Hill"},{"name":"Doctors Pond"},{"name":"Harbour Point"},{"name":"Lark Point"},{"name":"Booby Rock"},{"name":"Rainbow Cay"},{"name":"Remarkable Square Rock"},{"name":"Reef Harbour"},{"name":"Dolphin Head"},{"name":"Ball Rock"},{"name":"Port Nelson Salt Pond"},{"name":"Signal Point"},{"name":"Molasses Road"},{"name":"Matthew Town Road"},{"name":"Chancery Pond"},{"name":"The Bight of Acklins"},{"name":"Hog Island"},{"name":"Ragged Island Anchorage"},{"name":"Red Shank Point"},{"name":"Pelican Lake"},{"name":"Brown Cove"},{"name":"Borco Oil Terminal"},{"name":"Candle Cays"},{"name":"Scotts Cays"},{"name":"Lyford Cay Harbour"},{"name":"Little Pigeon Cay"},{"name":"Quintus Bar"},{"name":"The Hook"},{"name":"Shoe Hole Road"},{"name":"Douglas Passage"},{"name":"South Passage"},{"name":"Bush Cays"},{"name":"Sirius Rock"},{"name":"Victoria Point"},{"name":"Alcorine Cay"},{"name":"Leaf Cay"},{"name":"Croton Cay"},{"name":"Malabar Cays"},{"name":"Alabaster Bluff"},{"name":"Starve Creek"},{"name":"Eva's Cay"},{"name":"Green Turtle Cut"},{"name":"Tommy Young's Cay"},{"name":"Jewfish Cut"},{"name":"Clove Cay"},{"name":"Simon's Point"},{"name":"Davy Cay"},{"name":"Bock Cat Cay"},{"name":"West Pimblico Cays"},{"name":"East Pimblico Cays"},{"name":"Lansing Cays"},{"name":"Flamingo Bay"},{"name":"Joe Sound Creek"},{"name":"Castle Bluff"},{"name":"Dotham Cut"},{"name":"South Bimini Airport"},{"name":"George Town Exuma International Airport"},{"name":"San Salvador Airport"},{"name":"Pelican Bay At Lucaya"},{"name":"Club Peace and Plenty"},{"name":"Coral Sands Hotel"},{"name":"Breezes Bahamas"},{"name":"Pink Sands Hotel"},{"name":"British Colonial Hilton - Nassau"},{"name":"Island Palm Resort Hotel"},{"name":"Abaco Beach Resort & Boat Harbour"},{"name":"Nassau Palm Resort & Conference Center"},{"name":"One & Only Ocean Club"},{"name":"Graycliff Hotel And Restaurant"},{"name":"Best Western Castaways Resort & Suites"},{"name":"Romora Bay Club"},{"name":"The Bluff House Beach Hotel"},{"name":"Port Lucaya Resort & Yacht Club"},{"name":"Small Hope Bay Lodge"},{"name":"Island Seas Resort"},{"name":"Radisson Cable Beach"},{"name":"Royal Towers"},{"name":"Radisson Cable Beach Resort"},{"name":"Peace and Plenty Beach Inn"},{"name":"Atlantis Paradise Island Beach Tower"},{"name":"Wyndham Nassau Resort"},{"name":"The Cove Atlantis"},{"name":"The Abaco Club On Winding Bay"},{"name":"Dundee Bay Villas"},{"name":"The Bonefish Lodge"},{"name":"Grand Isle Resort and Spa"},{"name":"Harborside Resort at Atlantis"},{"name":"Gems At Paradise Resort"},{"name":"Orange Hill Beach Inn"},{"name":"Guanahani Village"},{"name":"Hawks Nest Resort & Marina"},{"name":"EMERALD PALMS HOTEL"},{"name":"Fernandez Bay Village"},{"name":"Pigeon Cay Beach Club"},{"name":"Viva Wyndham Fortuna Beach All Inclusive"},{"name":"Sammy T's Beach Resort"},{"name":"Stella Maris Resort Club"},{"name":"Sandyport Beaches Resort"},{"name":"Sandals Royal Bahamian Resort & Spa All Inclusive"},{"name":"Comfort Suites Paradise Island"},{"name":"Kamalame Cay"},{"name":"Bell Channel Inn"},{"name":"Westin Grand Bahama Island Our Lucaya Resort"},{"name":"Nassau Beach Hotel"},{"name":"Paradise Island Harbour Resort All Inclusive"},{"name":"Sheraton Grand Bahama Island Our Lucaya Resort"},{"name":"Red Carpet Inn Nassau"},{"name":"OLD BAHAMA BAY"},{"name":"FLAMINGO BAY YACHT CLUB AND MAR"},{"name":"TOWNE HOTEL"},{"name":"PELICAN BEACH VILLAS"},{"name":"GREEN TURTLE CLUB"},{"name":"VALENTINES RESORT HARBOUR ISLAN"},{"name":"FEBRUARY POINT RESORT"},{"name":"ROYAL PALM RESORT AND SUITES"},{"name":"FREEPORT RESORT AND CLUB"},{"name":"PINEAPPLE FIELDS HOTEL CONDO"},{"name":"RED APPLE BED AND BREAKFAST"},{"name":"BAHAMA BEACH CLUB RESORT"},{"name":"SANDALS ROYAL BAHAMIAN RESORT"},{"name":"HARBORSIDE RESORT AT ATLANTIS"},{"name":"QUALITY HOTEL CIGATOO"},{"name":"TREASURE CAY HOTEL RESORT   MAR"},{"name":"Lyford Cay Hospital"},{"name":"College of the Bahamas Oakes Field Campus"},{"name":"College of the Bahamas Northern Bahamas Campus"},{"name":"Staniel Cay yacht club"},{"name":"Highborne Cay"},{"name":"Alen cay"},{"name":"Sheraton Nassau Beach Resort"},{"name":"Spring Point Airport"},{"name":"Duncan Town Airport"},{"name":"Port Nelson Airport"},{"name":"Governor's Harbour Airport"},{"name":"Cat Cay Airport"},{"name":"Pitts Town Airport"},{"name":"Nassau Paradise Island Airport (historical)"},{"name":"Marsh Harbour Airport"},{"name":"Deadman's Cay Airport"},{"name":"Black Point District"},{"name":"Central Abaco District"},{"name":"Central Andros District"},{"name":"Central Eleuthera District"},{"name":"Crooked Island and Long Cay District"},{"name":"East Grand Bahama District"},{"name":"Grand Cay District"},{"name":"Hope Town District"},{"name":"Moore's Island District"},{"name":"North Abaco District"},{"name":"North Andros District"},{"name":"North Eleuthera District"},{"name":"South Abaco District"},{"name":"South Andros"},{"name":"South Eleuthera"},{"name":"Spanish Wells District"},{"name":"West Grand Bahama District"},{"name":"Cape Eleuthera Airport"},{"name":"George Town Airport"},{"name":"Moore's Island Airport"},{"name":"West End Airport"},{"name":"Folw Cay"},{"name":"Holmes Bay"},{"name":"Little Whale Cay Airport"},{"name":"Whale Cay Airfield"},{"name":"Rum Cay Airport (historical)"},{"name":"Castle Island Lighthouse"},{"name":"Great Inagua Lighthouse"},{"name":"North Point"},{"name":"Three Sisters"},{"name":"Northwest Point Lighthouse"},{"name":"Black Point Airport"},{"name":"Sampson Cay Airport"},{"name":"Little Darby Island Airport"},{"name":"Lee Stocking Airport"},{"name":"Ocean Cay Airport"},{"name":"Farmers Cay Airport"},{"name":"Leaf Cay Airport"},{"name":"Potters Cay"},{"name":"Nasau Harbor"},{"name":"Grantstown (Historical)"},{"name":"Cotton Bay Beach"},{"name":"Church Bay"},{"name":"Charles Bay"},{"name":"Red Pond"},{"name":"White Road Beach"},{"name":"Grand Bahama"},{"name":"Six Pack Pond"},{"name":"Duck Pond"},{"name":"Stout's Lake"},{"name":"Bird Rock Lighthouse"},{"name":"Dixon Hill Lighthouse"},{"name":"Unique Village"},{"name":"The Sugar Apple Bed And Breakfast"},{"name":"Treasure Cay Hotel Resort & Marina"},{"name":"Atlantis Royal Tower"},{"name":"Atlantis Coral Tower"},{"name":"B.W. Bay View Village"},{"name":"Melia Nassau Beach"},{"name":"Flamingo Bay Hotel & Marina"},{"name":"Ritz Beach Resort"},{"name":"Sunrise Resort & Marina"},{"name":"Ocean Reef Yacht Club & Resort"},{"name":"Radisson Our Lucaya Resort, Grand Bahama Island"},{"name":"Our Lucaya Reef Village"},{"name":"Royal Islander Hotel"},{"name":"Pelican Bay(Waterside Staterm)"},{"name":"Hideaways Exuma"},{"name":"Hideaways At Palm Bay"},{"name":"Bimini Bay Resort And Marina"},{"name":"Bahama Beach Club Resort"},{"name":"Hope Town Harbour Lodge"},{"name":"Atlantis The Reef"},{"name":"The Reef Atlantis Paradise Island"},{"name":"Riu Palace Paradise Island All Inclusive"},{"name":"One & Only Ocean Club Paradise Island"},{"name":"Grand Lucayan Bahamas Resort"},{"name":"Best Western Bay View Suites"},{"name":"Oceanfrontier Hideaway"},{"name":"The Reef At Atlantis"},{"name":"Bw Bay View Suites"},{"name":"Wyndham Nassau Resort & Crystal Palace Casino"},{"name":"Memories Grand Bahama Beach & Casino Resort"},{"name":"Unique Village Resort"},{"name":"Pink Sand Villas"},{"name":"Palm Bay Beach Club"},{"name":"Marlin At Taino Beach Resort"},{"name":"Pinksands Resort"},{"name":"Cape Eleuthera Resort & Yacht Club"},{"name":"Sandals Emerald Bay"},{"name":"Radisson Our Lucaya Beach & Golf Resort Hotel"},{"name":"Viva Wyndham Club Fortuna"},{"name":"Bonefish Bay Beach"},{"name":"Sandals Royal Bahamian Spa Resort&Offshore Island"},{"name":"Marley Resort And Spa"},{"name":"Silver Point Beach"},{"name":"Melia Nassau Beach Resort"},{"name":"Best Western Plus Bay View Suites"},{"name":"Atlantis Coral Towers"},{"name":"Atlantis Royal Towers"},{"name":"Sandals Emerald Bay Golf Tennis And Spa Resort"},{"name":"Bimini Big Game Club"},{"name":"Resorts World Bimini"},{"name":"Old Bahama Bay Resort & Yacht Harbour"},{"name":"Atlantis Paradise Island - Beach/ Coral/ Royal Tow"},{"name":"Grand Hyatt At Baha Mar"},{"name":"Gardens Nyc An Affinia Hotel"},{"name":"Holiday Inn Resort Nassau"},{"name":"Orchard Garden Hotel and Suites"},{"name":"Nassau Junkanoo Beach Resort"},{"name":"El Greco Hotel"},{"name":"Blue Water Resort"},{"name":"A Stone S Throw Away"},{"name":"Coco Plum Resorts Bahamas"},{"name":"Compass Point Beach Resort"},{"name":"The Baha Mar Casino and Hotel"},{"name":"Grand Lucayan Beach and Golf R"},{"name":"Powell Pointe Resort At Cape Eleuthera"},{"name":"Hotelviva Wyndham Fortuna Beach"},{"name":"Cape Eleuthera Resort and Marina"},{"name":"South Bimini Cay"},{"name":"Alec Cay"},{"name":"Tiamo Resort"},{"name":"Bimini North Seaplane Base"},{"name":"Corn Bay"},{"name":"Brown Bays"},{"name":"Canes Cay"},{"name":"Coconut Creek"},{"name":"Jobes Cay"},{"name":"Paul Mirac Rock"},{"name":"West End Cay"},{"name":"Highland Rock"},{"name":"Hut Cay"},{"name":"Mainland Cays"},{"name":"Steven Cays"},{"name":"Smith Cay Rocks"},{"name":"Moses Cay"},{"name":"Tom Brown Bay"},{"name":"Little Cub Cay"},{"name":"Outer Cay"},{"name":"John Cove Point"},{"name":"John Cove"},{"name":"Big Spence Rock"},{"name":"Little Spence Rock"},{"name":"Little Jerry Cay"},{"name":"Little Cross Cay"},{"name":"Bill Bride Cay"},{"name":"Bill Bride Creek"},{"name":"Big Mangrove Creek"},{"name":"Jonah Rock"},{"name":"Teeny Point"},{"name":"Big Cay Rock"},{"name":"Rock Harbour"},{"name":"Big Cut"},{"name":"Curry Cut"},{"name":"Elephant Rock"},{"name":"Randalls Cay"},{"name":"Ben Curry Rock"},{"name":"Ben Curry Creek"},{"name":"George Bluff"},{"name":"Maggoty Rock"},{"name":"Tampa Bay"},{"name":"Monkey Hill Point"},{"name":"Baba Point"},{"name":"Push Cay"},{"name":"Little Water Cay"},{"name":"Crab Cay Bluff"},{"name":"Nunjack Beach"},{"name":"Coconut Tree Bay"},{"name":"Nunjack Bluff"},{"name":"Nunjack Rocks"},{"name":"Trembling Pond"},{"name":"Mary Pond"},{"name":"Red Bay Point"},{"name":"Basin Harbour Cay"},{"name":"Goose Point"},{"name":"Basin Harbour"},{"name":"Pongo Carpet"},{"name":"Andrews Bluff"},{"name":"Mangrove Creek"},{"name":"Theresa Cay"},{"name":"Winding Bay Pond"},{"name":"Cup Leaf Point"},{"name":"Basin Harbour Point"},{"name":"East End"},{"name":"East Harbour"},{"name":"Gumelemi Cay"},{"name":"Sand Bank Point"},{"name":"Two Rocks"},{"name":"Treasure Cay Creek"},{"name":"Big Lake Creek"},{"name":"Long Bay Cay"},{"name":"Gillam Bay"},{"name":"Thurston Bay"},{"name":"Thurston Islet"},{"name":"Cocoa Bay"},{"name":"Joyless Point"},{"name":"White Sound"},{"name":"Black Sound Point"},{"name":"Black Sound"},{"name":"Settlement Point"},{"name":"Split Rock"},{"name":"Sand Banks Harbour"},{"name":"Okra Cay"},{"name":"Goliath Cay"},{"name":"Amos Bight"},{"name":"Amos Point"},{"name":"Amos Bluff"},{"name":"Red Shank Swash"},{"name":"Hills Creek"},{"name":"Lower Hill Cay"},{"name":"Nimble Creek"},{"name":"Rock Bluff"},{"name":"Sand Bank Cay"},{"name":"Fish Creek"},{"name":"Woolendean Rocks"},{"name":"Pigeon Cay Rock"},{"name":"Spirit Cay"},{"name":"Ballast Cay"},{"name":"Point of Bank Point"},{"name":"Levi Cay"},{"name":"Aaron Cay"},{"name":"Little Pelican Bush"},{"name":"Second Creek"},{"name":"First Creek"},{"name":"Sweet Bread Point"},{"name":"Big Coppice Point"},{"name":"Bloody Cay Bight"},{"name":"Big Coppice Mangrove"},{"name":"Sudy Mangrove"},{"name":"Sonny Cay"},{"name":"Matt Lowe Cay"},{"name":"Haul Over Cut"},{"name":"East Woolendean Cut"},{"name":"Delia's Cay"},{"name":"Minos Rock"},{"name":"Cistern Rock"},{"name":"Minos Cay"},{"name":"Daniel's Cay"},{"name":"Cormorant Pond"},{"name":"Joes Cay"},{"name":"Joes Creek"},{"name":"Two Sisters"},{"name":"Lower Turtle Rocks"},{"name":"Joes Bay"},{"name":"Blackwod Rock"},{"name":"Burnt Cay"},{"name":"Burnt Cay Bight"},{"name":"Don't Bluff Creek"},{"name":"Little Bill Bo Cay"},{"name":"Wills Cay Creek"},{"name":"Turtle Creek"},{"name":"Okra Creek"},{"name":"Okra Point"},{"name":"Big Tom Lowe Cay"},{"name":"Potato Cays"},{"name":"Wallace Creek"},{"name":"Bakers Creek"},{"name":"Chicken Point"},{"name":"Big Tom Lowe Bight"},{"name":"Big Bill Bo Cay"},{"name":"Little Tom Lowe Point"},{"name":"Little Potato Cay"},{"name":"Big Potato Cay"},{"name":"Carrion Crow Cay"},{"name":"Paddy's Head"},{"name":"Man-O-War Bush"},{"name":"Bustick Bight"},{"name":"Minus Cay"},{"name":"Pumpkin Bay"},{"name":"Cistern Creek"},{"name":"Israel Bay"},{"name":"Darville's Bay"},{"name":"Logger Head Creek"},{"name":"Red Rock Point"},{"name":"Little Tom Lowe Bight"},{"name":"Little Burnt Cay"},{"name":"Bibins Cay"},{"name":"Toucans Cay"},{"name":"Bevans Cay"},{"name":"Sparrowhawk Cay"},{"name":"Cambridge Harbour Cays"},{"name":"Meal Cay"},{"name":"Meal Cay Rocks"},{"name":"Curry Rock"},{"name":"Big Pelican Bush Rocks"},{"name":"Big Pelican Bush"},{"name":"Mastic Point Sound"},{"name":"Blue Hole Sound"},{"name":"Soap Point"},{"name":"Tavern Cay"},{"name":"Cooper Jack's Cay"},{"name":"Bakers Rock"},{"name":"Armstrong Cay"},{"name":"Pond Apple Cay"},{"name":"Black Point Cay"},{"name":"Buckaroon Bay"},{"name":"Johnies Cays"},{"name":"John Keys Cay"},{"name":"New Current Cay"},{"name":"John Doctor Cay"},{"name":"Mocking Bird Cay"},{"name":"Deep Sea Cay"},{"name":"Tuggy Cay"},{"name":"Bunks Cay"},{"name":"Nedds Cay"},{"name":"Broad Creek Cay"},{"name":"Davids Cay"},{"name":"Broad Creek"},{"name":"Peck Rocks"},{"name":"Cage Point"},{"name":"Pepper Cay"},{"name":"Dinner Cay"},{"name":"Senacord Creek"},{"name":"Middle Shoal"},{"name":"Lily Sand Bank"},{"name":"White Sand Ridge"},{"name":"Tea Table Cay"},{"name":"Carter Bank"},{"name":"Roberts Cut"},{"name":"West End Rocks"},{"name":"Guineaman Cay"},{"name":"Alec Cays"},{"name":"Dover Sound"},{"name":"Ganium's Cay"},{"name":"East End Bush"},{"name":"Mores Island Channel"},{"name":"Cormorant Rock"},{"name":"Spence Rock"},{"name":"Eldorado Shoal"},{"name":"Smiths Bay"},{"name":"Bight of Old Robinson"},{"name":"Goulding Cays"},{"name":"Hatchet Bay"},{"name":"Harry Creek Point"},{"name":"Naird Point"},{"name":"Barrel Rocks"},{"name":"Daniels Cay Rocks"},{"name":"Cay Sal Lighthouse"},{"name":"Crenula Cay"},{"name":"North Dangerous Shoal"},{"name":"Los Roques"},{"name":"West Water Cay"},{"name":"East Water Cay"},{"name":"South Dangerous Shoal"},{"name":"Bellows Cay"},{"name":"Anguilla Cay"},{"name":"Duncan Rock"},{"name":"Lake Forsyth"},{"name":"Stocking Harbour"},{"name":"Pigeon Creek"},{"name":"Bold Rock"},{"name":"Grape Tree Cay"},{"name":"Lower Channel Cay"},{"name":"Comer Rocks"},{"name":"Lansing Cay"},{"name":"Folly Bay"},{"name":"White Cliffs"},{"name":"The Going Through"},{"name":"Misery Point"},{"name":"Start Bay"},{"name":"Pitts Town Point"},{"name":"Salina Flat"},{"name":"Jack Bay"},{"name":"Grand Lucayan Lighthouse Pointe"},{"name":"Atlantis Coral Tower Ep"},{"name":"Black Sound Cay Reserve"},{"name":"Abaco National Park"},{"name":"The Retreat National Park"},{"name":"Harold and Wilson Ponds National Park"},{"name":"Primeval Forest National Park"},{"name":"Rand Nature Centre"},{"name":"Peterson Cay National Park"},{"name":"Lucayan National Park"},{"name":"Tilloo National Reserve"},{"name":"Conception Island National Park"},{"name":"Clifton Heritage Park"},{"name":"West Side National Park"},{"name":"Gun Cay Lighthouse"},{"name":"South Riding Rock Lighthouse"},{"name":"Elbow Cay Lighthouse"},{"name":"Abaco Lighthouse"},{"name":"Great Stirrup Cay Lighthouse"},{"name":"Bimini Lighthouse (historical)"},{"name":"Settlement Point Lighthouse (historical)"},{"name":"Old Yankee Cays"},{"name":"Thomas A. Robinson National Stadium"},{"name":"Baha Mar Resort"},{"name":"Great Isaac Lighthouse"},{"name":"Cay Lobos Lighthouse"}]