[{"name":"Beaumont"},{"name":"Bel Royal"},{"name":"Belle Vue"},{"name":"Creux Baillot"},{"name":"Five Oaks"},{"name":"Fliquet"},{"name":"Gorey"},{"name":"Grand Chemins"},{"name":"Grand Mourier"},{"name":"Grouville"},{"name":"L'Amiral"},{"name":"La Caroline"},{"name":"La Chesnee"},{"name":"La Corbiere"},{"name":"La Crabiere"},{"name":"La Falaise"},{"name":"La Fontaine"},{"name":"La Fosse"},{"name":"La Greve de Lecq"},{"name":"La Haule"},{"name":"La Hougue"},{"name":"La Porte"},{"name":"La Presse"},{"name":"La Pulente"},{"name":"La Robeline"},{"name":"La Saline"},{"name":"La Villaise"},{"name":"La Ville au Bas"},{"name":"La Ville Bagot"},{"name":"La Ville de L'Eglise"},{"name":"Le Bas de Lecq"},{"name":"Le Braye"},{"name":"Le Grouet"},{"name":"Le Hurrel"},{"name":"Le Mont es Croix"},{"name":"Le Port"},{"name":"Le Rondin"},{"name":"Leoville"},{"name":"Les Carrieres"},{"name":"Les Creux"},{"name":"Les Labeurs"},{"name":"Les Pallieres"},{"name":"Les Platons"},{"name":"Les St Germain"},{"name":"Les Vaux"},{"name":"Longueville"},{"name":"Lower Blanc Pignon"},{"name":"L'Etacq"},{"name":"Maufant"},{"name":"Millais"},{"name":"Millbrook"},{"name":"Mont Fiquet"},{"name":"Mont Mado"},{"name":"Perruque"},{"name":"Plemont"},{"name":"Portinfer"},{"name":"Rozel"},{"name":"Saint Aubin"},{"name":"Saint Clements"},{"name":"Saint John"},{"name":"Saint Ouen's Bay"},{"name":"Six Rues"},{"name":"St Brelade"},{"name":"St Lawrence"},{"name":"St Martin"},{"name":"St Mary's Village"},{"name":"St Ouen's Manor"},{"name":"St Ouen's Village"},{"name":"St Ouen Town"},{"name":"St Peters Village"},{"name":"St. Peters Arsenal"},{"name":"Trinity Manor"},{"name":"Trinity"},{"name":"Victoria Village"},{"name":"Vill es Normans"},{"name":"Ville es Nouaux"},{"name":"Ville des Quennevais"},{"name":"Vinchelez de Bas Manor"},{"name":"Vinchelez de Haut Manor"},{"name":"Le Hocq"},{"name":"La Moye"},{"name":"St Peter"},{"name":"Trodez"},{"name":"Violet Channel"},{"name":"Violet Bank"},{"name":"Vicard Point"},{"name":"Verclut Point"},{"name":"Vallee des Vaux"},{"name":"Tour de Rozel"},{"name":"Sorel Point"},{"name":"Saint Peter's Church"},{"name":"Saint Ouen's Pond"},{"name":"Saint John's Bay"},{"name":"Saint Helier"},{"name":"Saint Clements Bay"},{"name":"Saint Catherine Bay"},{"name":"Saint Brelade's Bay"},{"name":"Saint Aubins Bay"},{"name":"Rozel Bay"},{"name":"Rousse Rock"},{"name":"Rouge Nez Point"},{"name":"Rouge Nez"},{"name":"Ronez Point"},{"name":"Les Quennevais"},{"name":"Portelet Bay"},{"name":"Plemont Point"},{"name":"Plat Roque Point"},{"name":"Petit Port"},{"name":"Ile Percee"},{"name":"Noirmont Point"},{"name":"Les Sambues"},{"name":"Les Mouriers"},{"name":"Les Landes"},{"name":"Les Kaines"},{"name":"Les Ecrehou"},{"name":"Le Nez Point"},{"name":"Le Hocq Point"},{"name":"Point Le Fret"},{"name":"Point Le Croc"},{"name":"Pierres de Lecq"},{"name":"Le Couperon"},{"name":"La Thiebaut"},{"name":"La Rocque Point"},{"name":"L'Ane"},{"name":"Point La Moye"},{"name":"La Motte"},{"name":"La Hougue Boete"},{"name":"La Hougue Bie"},{"name":"La Crete Point"},{"name":"La Coupe Point"},{"name":"La Cotte Point"},{"name":"La Conchiere"},{"name":"La Colombiere"},{"name":"Bailiwick of Jersey"},{"name":"Jersey"},{"name":"Hermitage Rock"},{"name":"Ile au Guerdain"},{"name":"Grouville Bay"},{"name":"Grosnez Point"},{"name":"Greve de Lecq"},{"name":"Sand Eel Beach"},{"name":"Giffard Bay"},{"name":"Fremont Point"},{"name":"Fliquet Bay"},{"name":"Douet de la Mer"},{"name":"Les Dirouilles"},{"name":"Corbiere Point"},{"name":"Bouley Bay"},{"name":"Bouilly Port"},{"name":"Bonne Nuit Bay"},{"name":"Belle Hougue Point"},{"name":"Belcroute Bay"},{"name":"La Greve d' Azette"},{"name":"Anne Port"},{"name":"Aiguillon"},{"name":"Plateau des Minquiers"},{"name":"West Rock"},{"name":"Icho Bank"},{"name":"Plateau de la Frouquie"},{"name":"La Rousse Platte"},{"name":"L'Echiquelez"},{"name":"La Longy"},{"name":"Gros Etacs"},{"name":"La Grande Frouquie"},{"name":"La Rousse"},{"name":"Jinquet Rock"},{"name":"Rouget Rock"},{"name":"Margaret Rock"},{"name":"La Frouquie"},{"name":"Demie de Pas"},{"name":"Little Demie"},{"name":"La Coniere"},{"name":"L'teton"},{"name":"Rocque Herbeuse"},{"name":"Rocque Larron"},{"name":"Havre de Fontaines"},{"name":"La Sambue"},{"name":"La Trouee"},{"name":"Fort Henry"},{"name":"Fort William"},{"name":"Round Rouget"},{"name":"Bailhache"},{"name":"Flat Rock"},{"name":"La Ronde"},{"name":"Tas de Pois"},{"name":"Trois Grunes"},{"name":"Nipple Rock"},{"name":"Mondine"},{"name":"Dog's Nest Rock"},{"name":"Crabiere Rock"},{"name":"Havre des Pas"},{"name":"Point des Pas"},{"name":"East La Cloche"},{"name":"West La Cloche"},{"name":"South Reef"},{"name":"East Rock"},{"name":"Moulet Rock"},{"name":"Quereme Rock"},{"name":"Petite Mangeuse"},{"name":"Grande Mangeuse"},{"name":"Crapaud of the Mangeuse"},{"name":"Small Road"},{"name":"Sharp Rock"},{"name":"Platte Rock"},{"name":"Oyster Rocks"},{"name":"Hermitage Breakwater"},{"name":"Hinguette"},{"name":"Grunes Saint Michel"},{"name":"Fairway Rock"},{"name":"Ruaudiere Rock"},{"name":"Diamond Rock"},{"name":"Saint Helier Harbour"},{"name":"Mount Bingham"},{"name":"Crapaud of the Castle"},{"name":"Southeast Rock"},{"name":"Old Harbour"},{"name":"French Harbour"},{"name":"English Harbour"},{"name":"Saint Helier Marina"},{"name":"New North Quay"},{"name":"Albert Pier"},{"name":"South Pier"},{"name":"Victoria Pier"},{"name":"East Pier"},{"name":"West Breakwater"},{"name":"Les Buts"},{"name":"Crow Rock"},{"name":"Fort Elizabeth"},{"name":"Elizabeth Castle"},{"name":"Fort Charles"},{"name":"Gros du Chateau"},{"name":"Rocquemin"},{"name":"La Vrachiere"},{"name":"Baleine"},{"name":"La Collette Yacht Basin"},{"name":"Saint Clement"},{"name":"Saint Saviour"},{"name":"Les Tetards"},{"name":"Danger Rock"},{"name":"Grunes aux Dardes"},{"name":"Frouquie"},{"name":"Les Grunes du Port"},{"name":"Les Junees"},{"name":"Beach Rock"},{"name":"Saint Aubin's Fort"},{"name":"Grosse Rock"},{"name":"Les Poches a Suie"},{"name":"Grande Vaudin"},{"name":"Les Grunes Vaudin"},{"name":"Southwest Rock"},{"name":"Les Vracheres"},{"name":"Frouquie des Vracheres"},{"name":"Les Vraicquieres"},{"name":"Hubaut"},{"name":"Grande Grune"},{"name":"Petite Grune"},{"name":"Passage Rock"},{"name":"Banc Le Fret"},{"name":"Sillette"},{"name":"Noirs Hommes"},{"name":"Petit Four"},{"name":"Grand Four"},{"name":"Pignonet"},{"name":"Portelet Ledge"},{"name":"Point de But"},{"name":"Banc de Saint Brelade"},{"name":"Fourche"},{"name":"Fournier du Havre"},{"name":"Rocquet"},{"name":"Fournier Rock"},{"name":"Ouaisne Bay"},{"name":"Point Le Grouin"},{"name":"Beau Port"},{"name":"Fiquet Bay"},{"name":"Saint Brelade"},{"name":"Fort Regent"},{"name":"Saint Mary"},{"name":"Saint Lawrence"},{"name":"Saint Peter"},{"name":"Saint Ouen"},{"name":"Les Blanches Banques"},{"name":"Grosse Tete"},{"name":"Jument Rock"},{"name":"Noirmontaise Reef"},{"name":"Les Boiteaux"},{"name":"Green Rock"},{"name":"La Boue"},{"name":"Great Bank"},{"name":"Rigdon Bank"},{"name":"Petit Etaquerel"},{"name":"Grand Etaquerel"},{"name":"Swashway Channel"},{"name":"Mouilliere Rock"},{"name":"North East Rock"},{"name":"Banc Desormes"},{"name":"North West Head"},{"name":"Great Rock"},{"name":"East Reef"},{"name":"North Rock"},{"name":"North West Reef"},{"name":"South West Grune"},{"name":"La Grune de Lecq"},{"name":"Plemont Deep"},{"name":"Grune de Becquet"},{"name":"Grune de Douet"},{"name":"Grand Becquet"},{"name":"The Demies"},{"name":"Isle Agois"},{"name":"Crabbe"},{"name":"Le Col de la Rocque"},{"name":"Les Reuses"},{"name":"La Plaine Point"},{"name":"Le Fosse Vicq"},{"name":"La Houle"},{"name":"Grune de Vicq"},{"name":"Mourier Bay"},{"name":"La Lipende Point"},{"name":"Cormorant Rock"},{"name":"Cotil Point"},{"name":"Demie Rock"},{"name":"Shamrock Bank"},{"name":"Cheval Rock"},{"name":"Long Echet"},{"name":"Vicard Harbour"},{"name":"La Grune"},{"name":"L'Islet"},{"name":"L'Etaquerel"},{"name":"Les Troupeurs"},{"name":"Demie de la Tour"},{"name":"Nez du Guet"},{"name":"Hiaux"},{"name":"Brayes Rocks"},{"name":"Coupe Rock"},{"name":"Le Graveur"},{"name":"Pillon Rock"},{"name":"Eureka"},{"name":"Belval Cove"},{"name":"Le Ruau"},{"name":"La Hau"},{"name":"Joli"},{"name":"Le Foret"},{"name":"Le But"},{"name":"Les Burons"},{"name":"La Platte"},{"name":"Grune de South West"},{"name":"La Grese"},{"name":"Noire Roque"},{"name":"La Joie"},{"name":"Clump Rock"},{"name":"Les Grunes"},{"name":"Passe de l'Etoc"},{"name":"Grune de North West"},{"name":"Le Fierco"},{"name":"L'Etoc"},{"name":"Le Ruquet"},{"name":"Grande Rousse"},{"name":"Petite Rousse"},{"name":"Marmotier"},{"name":"Ile Maitre"},{"name":"Ecreviere Bank"},{"name":"Saint Martin"},{"name":"Banc du Chateau"},{"name":"Le Giffard"},{"name":"Grune Le Feuvre"},{"name":"La Grande Arconie"},{"name":"Grunes du Gris-Banc"},{"name":"Grune La Hauche"},{"name":"Black Rock"},{"name":"Jersey Airport"},{"name":"Jersey, Channel Islands"},{"name":"Grosnez Castle"},{"name":"Le Pinacle"},{"name":"Long Rock"},{"name":"Les Laveurs"},{"name":"Lewis Tower"},{"name":"Kempt Tower"},{"name":"Saint Peter's Mill"},{"name":"Le Val Rouget"},{"name":"Meulet Point"},{"name":"Le Sauchet"},{"name":"L'Ouziere"},{"name":"Square Fort"},{"name":"La Rocco Tower"},{"name":"Le Vermeux"},{"name":"La Rosiere"},{"name":"Val de la Mare Reservoir"},{"name":"Sillette Passage"},{"name":"THE SAVOY"},{"name":"Beachcombers Hotel"},{"name":"The Club Hotel & Spa"},{"name":"Hotel Cristina"},{"name":"Pomme d'Or Hotel"},{"name":"Merton Hotel"},{"name":"Golden Sands Hotel"},{"name":"Radisson SAS Waterfront Hotel"},{"name":"Hotel Revere"},{"name":"The Royal Yacht Hotel & Spa"},{"name":"Hotel Savoy"},{"name":"beausite"},{"name":"grand jersey"},{"name":"hampshire"},{"name":"l horizon"},{"name":"longueville manor"},{"name":"mayfair"},{"name":"metropole"},{"name":"mountview"},{"name":"old court house"},{"name":"shakespeare coast"},{"name":"somerville"},{"name":"stafford"},{"name":"the inn boutique"},{"name":"waters edge"},{"name":"Green Island Beach"},{"name":"Jersey Racecourse"},{"name":"Apollo Jersey"},{"name":"Best Western Royal"},{"name":"Cri"},{"name":"De France"},{"name":"De Normandie"},{"name":"Fort D'Auvergne Hotel"},{"name":"Gol"},{"name":"Grand Jersey Hotel & Spa"},{"name":"Greenhills Country Hotel"},{"name":"De Vere Grand Jersey"},{"name":"La Place"},{"name":"Les Ormes Leisure Resort"},{"name":"L'Horizon Beach Hotel & Spa"},{"name":"Marina Metro Hotel"},{"name":"Monterey"},{"name":"Ommaroo"},{"name":"The Fort D'Auvergne"},{"name":"The Metropole Hotel"},{"name":"The Monterey"},{"name":"Peterborough House"},{"name":"Radisson Blu Waterfront Hotel"},{"name":"Norfolk Lodge"},{"name":"Uplands Apartments"},{"name":"Runnymede Court Hotel"},{"name":"Samares Coast"},{"name":"Jubilee"},{"name":"The Forgotten Forest Arboretum"},{"name":"The Grand Jersey"},{"name":"Jersey Port"},{"name":"Queens (Jersey)"},{"name":"Portelet"},{"name":"Merton Hotel And Suites"},{"name":"Highfield Country"},{"name":"The Atlantic Hotel"},{"name":"Liberty Wharf Apartments By Bridgestreet"},{"name":"Chateau La Chaire"},{"name":"Mayfair Hotel St Helier"},{"name":"Metropole Hotel St Helier"},{"name":"Radisson Blu Waterfront St Helier"},{"name":"Maison Gorey Hotel"},{"name":"Talana Hotel"},{"name":"Greenhills Country Hotel & Restaurant"},{"name":"The Uplands Hotel"},{"name":"The Water's Edge"},{"name":"The Samares Coast Hotel"},{"name":"Undercliff Guest House"},{"name":"The Hampshire Hotel"},{"name":"Alhambra"},{"name":"The Dolphin Hotel"},{"name":"Bergerac"},{"name":"Beaufort"},{"name":"The Club Hotel and Spa Bohemia Restaurant"},{"name":"The Norfolk Lodge"},{"name":"Les Miellse Nature Reserve"},{"name":"Le Noir Pre"},{"name":"Les Monts"},{"name":"Model Aircraft Airfield"},{"name":"Gatehouse Ruins and World War II Bunker"},{"name":"Fremont Point TV Tower"}]